views/__init__.py
views/views.py
rest_framework_simplejwt-0.0.2.dist-info/LICENSE
rest_framework_simplejwt-0.0.2.dist-info/METADATA
rest_framework_simplejwt-0.0.2.dist-info/WHEEL
rest_framework_simplejwt-0.0.2.dist-info/top_level.txt
rest_framework_simplejwt-0.0.2.dist-info/RECORD
